surl/__init__.py
surl/__main__.py
surl-0.72.data/scripts/surl_cli.py
surl-0.72.data/scripts/surl_metrics.py
surl-0.72.data/scripts/surl_month_in_snaps.py
surl-0.72.data/scripts/surl_storeops.py
surl-0.72.dist-info/LICENSE
surl-0.72.dist-info/METADATA
surl-0.72.dist-info/WHEEL
surl-0.72.dist-info/top_level.txt
surl-0.72.dist-info/RECORD
