Metadata-Version: 2.1
Name: surl
Version: 0.72
Summary: Ubuntu Store API thin wrapper.
Home-page: https://github.com/cprov/surl
Author: Celso Providelo
Author-email: celso.providelo@canonical.com
License: GPL-3.0
Platform: UNKNOWN
Classifier: Programming Language :: Python :: 3
Classifier: License :: OSI Approved :: MIT License
Classifier: Operating System :: OS Independent
Requires-Dist: requests
Requires-Dist: pymacaroons
Requires-Dist: tabulate
Requires-Dist: iso8601
